mannetroll_cupyxturbo-0.1.4.dist-info/licenses/LICENSE
scipyturbo/__init__.py
scipyturbo/scipyturbo.icns
scipyturbo/turbo_crop.py
scipyturbo/turbo_main.py
scipyturbo/turbo_simulator.py
scipyturbo/turbo_simulator_cufft.py
scipyturbo/turbo_simulator_fps.py
scipyturbo/turbo_wrapper.py
scipyturbo/turbo_wrapper_nextdt.py
mannetroll_cupyxturbo-0.1.4.dist-info/METADATA
mannetroll_cupyxturbo-0.1.4.dist-info/WHEEL
mannetroll_cupyxturbo-0.1.4.dist-info/entry_points.txt
mannetroll_cupyxturbo-0.1.4.dist-info/top_level.txt
mannetroll_cupyxturbo-0.1.4.dist-info/RECORD
